ielearn/__init__.py
ielearn/batch_io.py
ielearn/util.py
ielearn/version.py
ielearn/extract/__init__.py
ielearn/extract/embedding.py
ielearn/extract/extract.py
ielearn/extract/xmp.py
ielearn/predict/__init__.py
ielearn/predict/feature_selection.py
ielearn/predict/predict.py
ielearn/predict/train.py
img_edit_learn-0.8.data/data/share/ielearn/README.rst
img_edit_learn-0.8.dist-info/LICENSE
img_edit_learn-0.8.dist-info/METADATA
img_edit_learn-0.8.dist-info/WHEEL
img_edit_learn-0.8.dist-info/top_level.txt
img_edit_learn-0.8.dist-info/RECORD
